datasloth
