Metadata-Version: 2.1
Name: datasloth
Version: 0.4
Summary: Natural language Pandas queries and data generation
Home-page: http://github.com/ibestvina/datasloth
Author: Ivan Bestvina
Author-email: ivan.bestvina@gmail.com
License: MIT
License-File: LICENSE
